dpkit/client.py
dpkit/models.py
dpkit/version.py
dpkit_client-0.0.2.dist-info/LICENSE
dpkit_client-0.0.2.dist-info/METADATA
dpkit_client-0.0.2.dist-info/NOTICE
dpkit_client-0.0.2.dist-info/WHEEL
dpkit_client-0.0.2.dist-info/top_level.txt
dpkit_client-0.0.2.dist-info/RECORD
