Metadata-Version: 2.1
Name: dpkit-client
Version: 0.0.2
Summary: Digital Pathology Development Kit Client
Author-email: Paige AI <eric.robert@paige.ai>
License: 
Classifier: Programming Language :: Python :: 3 :: Only
Classifier: Operating System :: OS Independent
Requires-Python: >=3.10
License-File: LICENSE
License-File: NOTICE
Requires-Dist: pydantic
Requires-Dist: requests
Requires-Dist: requests-toolbelt
Provides-Extra: all
Requires-Dist: dpkit-client[test]; extra == "all"
Provides-Extra: test
Requires-Dist: black; extra == "test"
Requires-Dist: flake8; extra == "test"
Requires-Dist: flake8-pyproject; extra == "test"
Requires-Dist: isort; extra == "test"
Requires-Dist: pytest; extra == "test"
